{
  "rig_name": "RKADE LightBrain MVP",
  "version": "0.1.0",
  "default_mode": "open_dance",
  "default_palette": "open_dance",
  "master_dimmer": 1.0,
  "target_fps": 40,
  "audio": {
    "device_index": null,
    "sample_rate": 48000,
    "block_size": 1024,
    "channels": 10,
    "input_gain": 3.0
  },
  "dmx": {
    "output": "mock",
    "serial_port": null,
    "baud_rate": 250000,
    "_note": "Set output to 'enttec' and serial_port to your COM port (e.g. 'COM9') for live hardware, or pass --serial COM9 on the CLI."
  },
  "fixtures": [
    {
      "id": "gigbar_001",
      "type": "gigbar_move_ils",
      "name": "GigBAR Move+ILS",
      "dmx_address": 1,
      "lane": "room",
      "group": "center",
      "personality": "51ch",
      "_personality_note": "Set fixture menu to 51Ch. Change to '29ch' if you need the shared-par bank mode.",
      "spot_pan_deg": 270,
      "spot_tilt_dmx": 90,
      "laser_enabled": false
    },
    {
      "id": "washfx2_l",
      "type": "wash_fx2",
      "name": "Wash FX 2 Left",
      "dmx_address": 52,
      "lane": "room",
      "group": "left",
      "_personality": "8Ch — Ch1=R Ch2=G Ch3=B Ch4=UV Ch5=Strobe Ch6=AutoProg Ch7=Speed Ch8=Dimmer"
    },
    {
      "id": "washfx2_r",
      "type": "wash_fx2",
      "name": "Wash FX 2 Right",
      "dmx_address": 60,
      "lane": "room",
      "group": "right",
      "_personality": "8Ch"
    },
    { "id": "rw_01", "type": "rockwedge", "name": "RockWedge 01", "dmx_address": 68,  "lane": "room", "group": "all" },
    { "id": "rw_02", "type": "rockwedge", "name": "RockWedge 02", "dmx_address": 76,  "lane": "room", "group": "all" },
    { "id": "rw_03", "type": "rockwedge", "name": "RockWedge 03", "dmx_address": 84,  "lane": "room", "group": "all" },
    { "id": "rw_04", "type": "rockwedge", "name": "RockWedge 04", "dmx_address": 92,  "lane": "room", "group": "all" },
    { "id": "rw_05", "type": "rockwedge", "name": "RockWedge 05", "dmx_address": 100, "lane": "room", "group": "all" },
    { "id": "rw_06", "type": "rockwedge", "name": "RockWedge 06", "dmx_address": 108, "lane": "room", "group": "all" },
    { "id": "rw_07", "type": "rockwedge", "name": "RockWedge 07", "dmx_address": 116, "lane": "room", "group": "all" },
    { "id": "rw_08", "type": "rockwedge", "name": "RockWedge 08", "dmx_address": 124, "lane": "room", "group": "all" },
    { "id": "rw_09", "type": "rockwedge", "name": "RockWedge 09", "dmx_address": 132, "lane": "room", "group": "all" },
    { "id": "rw_10", "type": "rockwedge", "name": "RockWedge 10", "dmx_address": 140, "lane": "room", "group": "all" },
    { "id": "rw_11", "type": "rockwedge", "name": "RockWedge 11", "dmx_address": 148, "lane": "room", "group": "all" },
    { "id": "rw_12", "type": "rockwedge", "name": "RockWedge 12", "dmx_address": 156, "lane": "room", "group": "all" },
    { "id": "rw_13", "type": "rockwedge", "name": "RockWedge 13", "dmx_address": 164, "lane": "room", "group": "all" },
    { "id": "rw_14", "type": "rockwedge", "name": "RockWedge 14", "dmx_address": 172, "lane": "room", "group": "all" },
    { "id": "rw_15", "type": "rockwedge", "name": "RockWedge 15", "dmx_address": 180, "lane": "room", "group": "all" },
    { "id": "rw_16", "type": "rockwedge", "name": "RockWedge 16", "dmx_address": 188, "lane": "room", "group": "all" },
    { "id": "rw_17", "type": "rockwedge", "name": "RockWedge 17", "dmx_address": 196, "lane": "room", "group": "all" },
    { "id": "rw_18", "type": "rockwedge", "name": "RockWedge 18", "dmx_address": 204, "lane": "room", "group": "all" }
  ]
}
